jjlocal/__init__.py
jjlocal/resources.py
jjlocal/subsystem/__init__.py
jjlocal/subsystem/common/__init__.py
jjlocal/subsystem/common/endereco/__init__.py
jjlocal/subsystem/common/endereco/resource.py
jjlocal/subsystem/parametrizacao/__init__.py
jjlocal/subsystem/parametrizacao/localidade/__init__.py
jjlocal/subsystem/parametrizacao/localidade/mesorregiao/__init__.py
jjlocal/subsystem/parametrizacao/localidade/mesorregiao/resource.py
jjlocal/subsystem/parametrizacao/localidade/microrregiao/__init__.py
jjlocal/subsystem/parametrizacao/localidade/microrregiao/resource.py
jjlocal/subsystem/parametrizacao/localidade/municipio/__init__.py
jjlocal/subsystem/parametrizacao/localidade/municipio/resource.py
jjlocal/subsystem/parametrizacao/localidade/pais/__init__.py
jjlocal/subsystem/parametrizacao/localidade/pais/resource.py
jjlocal/subsystem/parametrizacao/localidade/regiao/__init__.py
jjlocal/subsystem/parametrizacao/localidade/regiao/resource.py
jjlocal/subsystem/parametrizacao/localidade/uf/__init__.py
jjlocal/subsystem/parametrizacao/localidade/uf/resource.py
jjlocal/subsystem/sysadmin/__init__.py
jjlocal/subsystem/sysadmin/ibge_sync/__init__.py
jjlocal/subsystem/sysadmin/ibge_sync/manager.py
jjlocal/subsystem/sysadmin/ibge_sync/resource.py
jjlocal-1.0.0.dist-info/AUTHORS
jjlocal-1.0.0.dist-info/METADATA
jjlocal-1.0.0.dist-info/WHEEL
jjlocal-1.0.0.dist-info/top_level.txt
jjlocal-1.0.0.dist-info/RECORD
