Metadata-Version: 2.1
Name: jjlocal
Version: 1.0.0
Summary: JJLocal backend Flask REST service
Home-page: UNKNOWN
License: UNKNOWN
Platform: UNKNOWN
License-File: AUTHORS
Requires-Dist: jjsystem <2.0.0,>=1.0.0
Requires-Dist: flask-cors
